Metadata-Version: 2.1
Name: automatedqa
Version: 0.0.1
Summary: Execute specific commands in browser with selenium for QA test.
Home-page: https://github.com/brenokcc
Author: Breno Silva
Author-email: brenokcc@yahoo.com.br
License: BSD License
Classifier: Environment :: Web Environment
Classifier: Intended Audience :: Developers
Classifier: License :: OSI Approved :: BSD License
Classifier: Operating System :: OS Independent
Classifier: Programming Language :: Python
Classifier: Topic :: Internet :: WWW/HTTP
Classifier: Topic :: Internet :: WWW/HTTP :: Dynamic Content
